scalpg_dump/__init__.py
scalpg_dump/scalpg_dump.py
scalpg_dump-0.1.2.dist-info/DESCRIPTION.rst
scalpg_dump-0.1.2.dist-info/METADATA
scalpg_dump-0.1.2.dist-info/RECORD
scalpg_dump-0.1.2.dist-info/WHEEL
scalpg_dump-0.1.2.dist-info/entry_points.txt
scalpg_dump-0.1.2.dist-info/metadata.json
scalpg_dump-0.1.2.dist-info/top_level.txt
