Metadata-Version: 2.0
Name: scalpg-dump
Version: 0.1.2
Summary: Dumps your Scalingo PostgreSQL database without the hustle
Home-page: https://github.com/tobiase/scalpg_dump
Author: Tobias Englert
Author-email: tobias@englert.it
License: MIT license
Keywords: scalpg_dump
Platform: UNKNOWN
Classifier: Development Status :: 2 - Pre-Alpha
Classifier: Intended Audience :: Developers
Classifier: License :: OSI Approved :: MIT License
Classifier: Natural Language :: English
Classifier: Programming Language :: Python :: 3
Classifier: Programming Language :: Python :: 3.3
Classifier: Programming Language :: Python :: 3.4
Classifier: Programming Language :: Python :: 3.5
Classifier: Programming Language :: Python :: 3.6
Requires-Dist: dj-database-url
